elsie/__init__.py
elsie/version.py
elsie/boxtree/__init__.py
elsie/boxtree/box.py
elsie/boxtree/boxitem.py
elsie/boxtree/boxmixin.py
elsie/boxtree/layout.py
elsie/boxtree/lazy.py
elsie/boxtree/value.py
elsie/ext/__init__.py
elsie/ext/export.py
elsie/ext/latex.py
elsie/ext/list.py
elsie/ext/markdown.py
elsie/ext/todo.py
elsie/render/__init__.py
elsie/render/image.py
elsie/render/inkscape.py
elsie/render/jupyter.py
elsie/render/ora.py
elsie/render/pdfmerge.py
elsie/render/render.py
elsie/render/backends/__init__.py
elsie/render/backends/backend.py
elsie/render/backends/rcontext.py
elsie/render/backends/cairo/__init__.py
elsie/render/backends/cairo/backend.py
elsie/render/backends/cairo/draw.py
elsie/render/backends/cairo/rcontext.py
elsie/render/backends/cairo/shapes.py
elsie/render/backends/cairo/svg.py
elsie/render/backends/cairo/text.py
elsie/render/backends/cairo/utils.py
elsie/render/backends/svg/__init__.py
elsie/render/backends/svg/backend.py
elsie/render/backends/svg/draw.py
elsie/render/backends/svg/query.py
elsie/render/backends/svg/rcontext.py
elsie/render/backends/svg/utils.py
elsie/shapes/__init__.py
elsie/shapes/arrow.py
elsie/shapes/path.py
elsie/slides/__init__.py
elsie/slides/show.py
elsie/slides/slide.py
elsie/slides/slidedeck.py
elsie/text/__init__.py
elsie/text/highlight.py
elsie/text/stylecontainer.py
elsie/text/textboxitem.py
elsie/text/textparser.py
elsie/text/textstyle.py
elsie/utils/__init__.py
elsie/utils/cache.py
elsie/utils/files.py
elsie/utils/geom.py
elsie/utils/sxml.py
elsie-3.4.dist-info/LICENSE
elsie-3.4.dist-info/METADATA
elsie-3.4.dist-info/WHEEL
elsie-3.4.dist-info/top_level.txt
elsie-3.4.dist-info/RECORD
